xiaoyanshitool
