Metadata-Version: 1.0
Name: xiaoyanshitool
Version: 0.0.9
Summary: some useful api for xiaoyanshi and xiaoxingxing, add ScrathAPI 
Home-page: https://github.com/SmileLikeYe
Author: Smile
Author-email: smiletoye@gmail.com
License: UNKNOWN
Keywords: python excel scrath
Platform: UNKNOWN
